README.rst
setup.cfg
setup.py
common/__init__.py
common/templatetags/__init__.py
common/templatetags/common_tags.py
common_tags.egg-info/PKG-INFO
common_tags.egg-info/SOURCES.txt
common_tags.egg-info/dependency_links.txt
common_tags.egg-info/not-zip-safe
common_tags.egg-info/requires.txt
common_tags.egg-info/top_level.txt