Metadata-Version: 1.1
Name: common-tags
Version: 1.0.3
Summary: Common templatetags provides for Django
Home-page: https://github.com/agusmakmun/common-tags/
Author: Agus Makmun (Summon Agus)
Author-email: agus@python.web.id
License: MIT
Download-URL: https://github.com/agusmakmun/common-tags/tarball/v1.0.3
Keywords: django common templatetags,django templatetags
Platform: UNKNOWN
Classifier: Development Status :: 5 - Production/Stable
Classifier: Environment :: Web Environment
Classifier: Programming Language :: Python
Classifier: Programming Language :: Python :: 2.7
Classifier: Programming Language :: Python :: 3.3
Classifier: Programming Language :: Python :: 3.4
Classifier: Programming Language :: Python :: 3.5
Classifier: License :: OSI Approved :: MIT License
Classifier: Operating System :: OS Independent
Classifier: Intended Audience :: Developers
Classifier: Framework :: Django
